{
  "animateLoading": true,
  "borderRadius": "{{appsmith.theme.borderRadius.appBorderRadius}}",
  "bottomRow": 16,
  "boxShadow": "none",
  "defaultImage": "https://assets.appsmith.com/widgets/default.png",
  "dynamicBindingPathList": [
    {
      "key": "borderRadius"
    }
  ],
  "dynamicTriggerPathList": [],
  "enableDownload": false,
  "enableRotation": false,
  "flexVerticalAlignment": "start",
  "image": "https://upload.wikimedia.org/wikipedia/commons/thumb/1/1a/2023_Dysk_SSD_Patriot_P210_2TB.jpg/1280px-2023_Dysk_SSD_Patriot_P210_2TB.jpg",
  "imageShape": "RECTANGLE",
  "isLoading": false,
  "isVisible": true,
  "key": "s8ffvju7kp",
  "leftColumn": 1,
  "maxZoomLevel": 1,
  "mobileBottomRow": 15,
  "mobileLeftColumn": 10,
  "mobileRightColumn": 22,
  "mobileTopRow": 3,
  "needsErrorInfo": false,
  "objectFit": "cover",
  "parentColumnSpace": 7.34375,
  "parentId": "m3mr2nsowx",
  "parentRowSpace": 10,
  "renderMode": "CANVAS",
  "rightColumn": 20,
  "topRow": 0,
  "type": "IMAGE_WIDGET",
  "version": 1,
  "widgetId": "scab9335sn",
  "widgetName": "Image1Copy1Copy6"
}