{
  "gitSyncId": "69b1b33eb387763859c839de_02a95c9a-9d6f-42bc-8788-dfa2b3764a73",
  "id": "AddParts_UpdateCase",
  "pluginId": "restapi-plugin",
  "pluginType": "API",
  "unpublishedAction": {
    "actionConfiguration": {
      "autoGeneratedHeaders": [
        {
          "key": "content-type",
          "value": "application/json"
        }
      ],
      "body": "{\n  \"brand\": \"{{ EditBrandCase.text }}\",\n  \"model\": \"{{ EditModelCase.text }}\",\n  \"price\": {{ Number(EditPriceCase.text) }},\n}",
      "bodyFormData": [],
      "encodeParamsToggle": true,
      "formData": {
        "apiContentType": "application/json"
      },
      "headers": [],
      "httpMethod": "PUT",
      "httpVersion": "HTTP11",
      "paginationType": "NONE",
      "path": "/casess/{{appsmith.store.selectedPartId}}",
      "pluginSpecifiedTemplates": [
        {
          "value": true
        }
      ],
      "queryParameters": [],
      "timeoutInMillisecond": 10000
    },
    "confirmBeforeExecute": false,
    "datasource": {
      "id": "PCPartsAPI",
      "isAutoGenerated": false,
      "name": "PCPartsAPI",
      "pluginId": "restapi-plugin"
    },
    "dynamicBindingPathList": [
      {
        "key": "body"
      },
      {
        "key": "path"
      }
    ],
    "name": "UpdateCase",
    "pageId": "AddParts",
    "runBehaviour": "MANUAL",
    "userSetOnLoad": false
  }
}