{
  "gitSyncId": "69ae2a99bda09d75b640915b_549f6899-ec1f-4582-95f9-75ea5305a831",
  "id": "Preferences_PreferencesForm.save",
  "pluginId": "js-plugin",
  "pluginType": "JS",
  "unpublishedAction": {
    "actionConfiguration": {
      "encodeParamsToggle": true,
      "jsArguments": [],
      "paginationType": "NONE",
      "timeoutInMillisecond": 10000
    },
    "collectionId": "Preferences_PreferencesForm",
    "confirmBeforeExecute": false,
    "datasource": {
      "isAutoGenerated": false,
      "name": "UNUSED_DATASOURCE",
      "pluginId": "js-plugin"
    },
    "dynamicBindingPathList": [
      {
        "key": "body"
      }
    ],
    "fullyQualifiedName": "PreferencesForm.save",
    "name": "save",
    "pageId": "Preferences",
    "runBehaviour": "MANUAL",
    "userSetOnLoad": false
  }
}